libpurecoollink/__init__.py
libpurecoollink/const.py
libpurecoollink/dyson.py
libpurecoollink/dyson_360_eye.py
libpurecoollink/dyson_device.py
libpurecoollink/dyson_pure_cool_link.py
libpurecoollink/dyson_pure_hotcool_link.py
libpurecoollink/dyson_pure_state.py
libpurecoollink/exceptions.py
libpurecoollink/utils.py
libpurecoollink/zeroconf.py
libpurecoollink-0.4.2.dist-info/DESCRIPTION.rst
libpurecoollink-0.4.2.dist-info/METADATA
libpurecoollink-0.4.2.dist-info/RECORD
libpurecoollink-0.4.2.dist-info/WHEEL
libpurecoollink-0.4.2.dist-info/metadata.json
libpurecoollink-0.4.2.dist-info/top_level.txt
libpurecoollink-0.4.2.dist-info/zip-safe
