Metadata-Version: 2.0
Name: libpurecoollink
Version: 0.4.2
Summary: Dyson Pure Cool/Hot+Cool Link and 360 eye robot vacuum devices Python library
Home-page: http://libpurecoollink.readthedocs.io
Author: Charles Blonde
Author-email: charles.blonde@gmail.com
License: Apache License 2.0
Download-URL: https://github.com/CharlesBlonde/libpurecoollink
Keywords: dyson,purecoollink,eye360,purehotcoollink
Platform: any
Classifier: Intended Audience :: Developers
Classifier: License :: OSI Approved :: Apache Software License
Classifier: Operating System :: OS Independent
Classifier: Programming Language :: Python :: 3.6
Classifier: Programming Language :: Python :: 3.5
Classifier: Programming Language :: Python :: 3.4
Classifier: Topic :: Software Development :: Libraries
Requires-Dist: netifaces
Requires-Dist: paho-mqtt
Requires-Dist: pycryptodome
Requires-Dist: requests (>=2,<3)
Requires-Dist: six
